MANIFEST.in
README.md
setup.py
staff/__init__.py
staff/admin.py
staff/app_registry.py
staff/feeds.py
staff/forms.py
staff/managers.py
staff/models.py
staff/search_indexes.py
staff/settings.json
staff/signals.py
staff/urls.py
staff/views.py
staff/migrations/0001_initial.py
staff/migrations/0002_auto__del_field_staff_start_date__del_field_staff_slideshare__del_fiel.py
staff/migrations/0003_auto__add_field_staff_ordering.py
staff/migrations/0004_auto__chg_field_department_name__chg_field_position_name.py
staff/migrations/0005_auto__add_field_staff_position__chg_field_stafffile_position.py
staff/migrations/0006_migrate_ordering.py
staff/migrations/0007_auto__del_field_staff_ordering.py
staff/migrations/__init__.py
staff/static/css/staff.css
staff/static/images/staff-default.jpg
staff/templates/search/indexes/staff/staff_text.txt
staff/templates/staff/base.html
staff/templates/staff/cv.html
staff/templates/staff/meta.html
staff/templates/staff/options.html
staff/templates/staff/search-form.html
staff/templates/staff/search-result.html
staff/templates/staff/search.html
staff/templates/staff/view.html
staff/templatetags/__init__.py
staff/templatetags/staff_tags.py
tendenci_staff.egg-info/PKG-INFO
tendenci_staff.egg-info/SOURCES.txt
tendenci_staff.egg-info/dependency_links.txt
tendenci_staff.egg-info/requires.txt
tendenci_staff.egg-info/top_level.txt